pypandas_sql/__init__.py
pypandas_sql/dbconnector/__init__.py
pypandas_sql/dbconnector/db_connector.py
pypandas_sql/dbconnector/redshift_connector.py
pypandas_sql/queryengine/__init__.py
pypandas_sql/queryengine/db_query_engine.py
pypandas_sql/queryengine/redshift_query_engine.py
pypandas_sql-0.0.1.data/scripts/pypandasql
tests/__init__.py
tests/persistent_test_base.py
tests/redshift_model.py
tests/redshift_persistent_test_base.py
tests/test_hello.py
tests/pypandas_sql/__init__.py
tests/pypandas_sql/dbconnector/__init__.py
tests/pypandas_sql/dbconnector/db_connector_test.py
tests/pypandas_sql/dbconnector/redshift_connector_test.py
tests/pypandas_sql/queryengine/__init__.py
tests/pypandas_sql/queryengine/db_query_engine_test.py
tests/pypandas_sql/queryengine/redshift_query_engine_test.py
tests/utils/__init__.py
tests/utils/config_helper_test.py
tests/utils/credential_helper_test.py
tests/utils/filepath_helper_test.py
utils/__init__.py
utils/config_helper.py
utils/credential_helper.py
utils/filepath_helper.py
pypandas_sql-0.0.1.dist-info/LICENSE
pypandas_sql-0.0.1.dist-info/METADATA
pypandas_sql-0.0.1.dist-info/WHEEL
pypandas_sql-0.0.1.dist-info/top_level.txt
pypandas_sql-0.0.1.dist-info/RECORD
