Metadata-Version: 2.1
Name: pypandas_sql
Version: 0.0.1
Summary: Utility to read/write data from various data sources
Home-page: https://github.com/saurabhdhupar/pypandas-sql
Author: Saurabh Dhupar
Author-email: saurabh.dhupar@gmail.com
License: UNKNOWN
Platform: UNKNOWN
Classifier: Programming Language :: Python :: 3
Classifier: License :: OSI Approved :: MIT License
Classifier: Operating System :: OS Independent
Requires-Python: >=3
